infinote/__init__.py
infinote/buffer_handling.py
infinote/config.py
infinote/key_handler.py
infinote/main.py
infinote/persistence.py
infinote/required.vim
infinote/text_object.py
infinote/view.py
infinote_md-0.4.3.dist-info/METADATA
infinote_md-0.4.3.dist-info/WHEEL
infinote_md-0.4.3.dist-info/entry_points.txt
infinote_md-0.4.3.dist-info/top_level.txt
infinote_md-0.4.3.dist-info/RECORD
