Metadata-Version: 2.1
Name: infinote-md
Version: 0.4.3
Summary: Feel the spatial freedom in your notes.
Home-page: https://github.com/filyp/infinote
Author: Filip Sondej
Classifier: Programming Language :: Python :: 3
Classifier: Programming Language :: Python :: 3.11
Classifier: License :: OSI Approved :: GNU Lesser General Public License v3 (LGPLv3)
Classifier: Operating System :: OS Independent
Requires-Python: >=3.10
Requires-Dist: PySide6
Requires-Dist: pynvim
Requires-Dist: colormath
Requires-Dist: boltons
